LICENSE
README.md
setup.cfg
setup.py
scripts/build_app.py
src/hydrodashboards/__init__.py
src/hydrodashboards/build_css_templates.py
src/hydrodashboards/build_html_templates.py
src/hydrodashboards.egg-info/PKG-INFO
src/hydrodashboards.egg-info/SOURCES.txt
src/hydrodashboards.egg-info/dependency_links.txt
src/hydrodashboards.egg-info/requires.txt
src/hydrodashboards.egg-info/top_level.txt
src/hydrodashboards/bokeh/__init__.py
src/hydrodashboards/bokeh/build_cache.py
src/hydrodashboards/bokeh/config.json
src/hydrodashboards/bokeh/config.py
src/hydrodashboards/bokeh/data.py
src/hydrodashboards/bokeh/language.py
src/hydrodashboards/bokeh/log_utils.py
src/hydrodashboards/bokeh/main.py
src/hydrodashboards/bokeh/sources.py
src/hydrodashboards/bokeh/theme.yaml
src/hydrodashboards/bokeh/static/css/styles.css
src/hydrodashboards/bokeh/static/css/styles_dark.css
src/hydrodashboards/bokeh/static/icons/arrow_down.png
src/hydrodashboards/bokeh/static/icons/arrow_left.png
src/hydrodashboards/bokeh/static/icons/arrow_right.png
src/hydrodashboards/bokeh/static/icons/arrow_up.png
src/hydrodashboards/bokeh/static/icons/download.png
src/hydrodashboards/bokeh/static/icons/history.png
src/hydrodashboards/bokeh/static/icons/layers.svg
src/hydrodashboards/bokeh/static/icons/refresh.png
src/hydrodashboards/bokeh/static/icons/refresh_filters.png
src/hydrodashboards/bokeh/static/icons/save.png
src/hydrodashboards/bokeh/static/icons/search.png
src/hydrodashboards/bokeh/static/icons/threshold.png
src/hydrodashboards/bokeh/static/js/bootstrap.bundle.js
src/hydrodashboards/bokeh/static/js/bootstrap.bundle.js.map
src/hydrodashboards/bokeh/static/js/bootstrap.bundle.min.js
src/hydrodashboards/bokeh/static/js/bootstrap.bundle.min.js.map
src/hydrodashboards/bokeh/static/js/bootstrap.esm.js
src/hydrodashboards/bokeh/static/js/bootstrap.esm.js.map
src/hydrodashboards/bokeh/static/js/bootstrap.esm.min.js
src/hydrodashboards/bokeh/static/js/bootstrap.esm.min.js.map
src/hydrodashboards/bokeh/static/js/bootstrap.js
src/hydrodashboards/bokeh/static/js/bootstrap.js.map
src/hydrodashboards/bokeh/static/js/bootstrap.min.js
src/hydrodashboards/bokeh/static/js/bootstrap.min.js.map
