Metadata-Version: 2.1
Name: hydrodashboards
Version: 0.6.0
Summary: Dashboards for Hydro Data
Author: Daniel Tollenaar
Author-email: daniel@d2hydro.nl
Requires-Python: >=3.9
Provides-Extra: test
Provides-Extra: docs
License-File: LICENSE
